dmtri/__init__.py
dmtri/cli.py
dmtri/doctor.py
dmtri/execution_plan.py
dmtri/paths.py
dmtri/utils.py
dmtri/hooks/__init__.py
dmtri/hooks/hooks.py
dmtri-0.1.0.dist-info/METADATA
dmtri-0.1.0.dist-info/WHEEL
dmtri-0.1.0.dist-info/entry_points.txt
dmtri-0.1.0.dist-info/top_level.txt
dmtri-0.1.0.dist-info/RECORD
