Metadata-Version: 2.4
Name: dmtri
Version: 0.1.0
Summary: CLI tool for triggering datacenter metadata updates
Author-email: Nikos Sokos <nsokos@noa.com>
Requires-Python: >=3.8
Requires-Dist: ansible>=6.7.0
Requires-Dist: ansible-runner>=2.3.6
Requires-Dist: appdirs>=1.4.4
Requires-Dist: pytest>=8.3.5
Requires-Dist: pytest-cov>=5.0.0
Requires-Dist: requests
Requires-Dist: tomli>=2.2.1
